dealfolio/__init__.py
dealfolio-0.0.1.dist-info/METADATA
dealfolio-0.0.1.dist-info/WHEEL
dealfolio-0.0.1.dist-info/top_level.txt
dealfolio-0.0.1.dist-info/RECORD
