Metadata-Version: 2.4
Name: dealfolio
Version: 0.0.1
Summary: Name reserved for future Dealfolio release.
Author-email: Wes McKinney <info@wesmckinney.com>
Classifier: Programming Language :: Python :: 3
Classifier: Programming Language :: Python :: 3 :: Only
Classifier: Development Status :: 1 - Planning
Classifier: License :: OSI Approved :: GNU Affero General Public License v3
Requires-Python: >=3.10
